saseanalytics
