Metadata-Version: 2.1
Name: saseanalytics
Version: 0.2
Summary: my the package in python
Home-page: https://github.com/Michaelkre/saseanalitic
Author: kre kadjo michael
Author-email: mkre1999@gmail.com
License: MIT
Download-URL: https://github.com/Michaelkre/saseanalitic/archive/refs/tags/v_0.2.tar.gz
Keywords: SOME,MEANINGFULL,KEYWORDS
Platform: UNKNOWN
Classifier: Development Status :: 3 - Alpha
Classifier: Intended Audience :: Developers
Classifier: Topic :: Software Development :: Build Tools
Classifier: License :: OSI Approved :: MIT License
Classifier: Programming Language :: Python :: 3
Classifier: Programming Language :: Python :: 3.4
Classifier: Programming Language :: Python :: 3.5
Classifier: Programming Language :: Python :: 3.6
License-File: LICENSE.txt
